LICENSE.md
MANIFEST.in
Makefile
README.md
requirements.txt
setup.py
bwa/.git
bwa/.gitignore
bwa/.travis.yml
bwa/COPYING
bwa/ChangeLog
bwa/Makefile
bwa/NEWS.md
bwa/QSufSort.c
bwa/QSufSort.h
bwa/QSufSort.o
bwa/README-alt.md
bwa/README.md
bwa/bamlite.c
bwa/bamlite.h
bwa/bntseq.c
bwa/bntseq.h
bwa/bntseq.o
bwa/bwa.1
bwa/bwa.c
bwa/bwa.h
bwa/bwa.o
bwa/bwamem.c
bwa/bwamem.h
bwa/bwamem.o
bwa/bwamem_extra.c
bwa/bwamem_extra.o
bwa/bwamem_pair.c
bwa/bwamem_pair.o
bwa/bwape.c
bwa/bwase.c
bwa/bwase.h
bwa/bwaseqio.c
bwa/bwashm.c
bwa/bwt.c
bwa/bwt.h
bwa/bwt.o
bwa/bwt_gen.c
bwa/bwt_gen.o
bwa/bwt_lite.c
bwa/bwt_lite.h
bwa/bwtaln.c
bwa/bwtaln.h
bwa/bwtgap.c
bwa/bwtgap.h
bwa/bwtindex.c
bwa/bwtindex.o
bwa/bwtsw2.h
bwa/bwtsw2_aux.c
bwa/bwtsw2_chain.c
bwa/bwtsw2_core.c
bwa/bwtsw2_main.c
bwa/bwtsw2_pair.c
bwa/example.c
bwa/fastmap.c
bwa/is.c
bwa/is.o
bwa/kbtree.h
bwa/khash.h
bwa/kopen.c
bwa/kseq.h
bwa/ksort.h
bwa/kstring.c
bwa/kstring.h
bwa/kstring.o
bwa/ksw.c
bwa/ksw.h
bwa/ksw.o
bwa/kthread.c
bwa/kthread.o
bwa/kvec.h
bwa/libbwa.a
bwa/main.c
bwa/malloc_wrap.c
bwa/malloc_wrap.h
bwa/malloc_wrap.o
bwa/maxk.c
bwa/pemerge.c
bwa/qualfa2fq.pl
bwa/rle.c
bwa/rle.h
bwa/rle.o
bwa/rope.c
bwa/rope.h
bwa/rope.o
bwa/utils.c
bwa/utils.h
bwa/utils.o
bwa/xa2multi.pl
bwa/bwakit/README.md
bwa/bwakit/bwa-postalt.js
bwa/bwakit/run-HLA
bwa/bwakit/run-bwamem
bwa/bwakit/run-gen-ref
bwa/bwakit/typeHLA-selctg.js
bwa/bwakit/typeHLA.js
bwa/bwakit/typeHLA.sh
bwapy/__init__.py
bwapy/libbwa.py
bwapy/libbwapy.c
bwapy/memopts.c
bwapy.egg-info/PKG-INFO
bwapy.egg-info/SOURCES.txt
bwapy.egg-info/dependency_links.txt
bwapy.egg-info/entry_points.txt
bwapy.egg-info/not-zip-safe
bwapy.egg-info/requires.txt
bwapy.egg-info/top_level.txt